{"lastUsed":1592904630129,"path":"D:\/codes\/algorithm","projectCount":6,"recentFiles":[{"path":"\/codeplus_algo_basic\/src\/data_structure_ref","parentWorkspace":"D:\/codes\/algorithm","name":"postOrder2_stack.java","lastModified":1592889984245,"locationURI":"file:\/D:\/codes\/algorithm\/codeplus_algo_basic\/src\/data_structure_ref\/postOrder2_stack.java"},{"path":"\/Algorithm_Study\/src\/graph_and_tree","parentWorkspace":"D:\/codes\/algorithm","name":"confirm_BinaryTree.java","lastModified":1589296302839,"locationURI":"file:\/D:\/codes\/algorithm\/Algorithm_Study\/src\/graph_and_tree\/confirm_BinaryTree.java"},{"path":"\/codeplus_algo_basic\/src\/data_structure_ref","parentWorkspace":"D:\/codes\/algorithm","name":"four_num.java","lastModified":1592897580928,"locationURI":"file:\/D:\/codes\/algorithm\/codeplus_algo_basic\/src\/data_structure_ref\/four_num.java"},{"path":"\/Algorithm_Study\/src\/data_structure","parentWorkspace":"D:\/codes\/algorithm","name":"binarySearch.java","lastModified":1592625481769,"locationURI":"file:\/D:\/codes\/algorithm\/Algorithm_Study\/src\/data_structure\/binarySearch.java"},{"path":"\/Programmers\/src\/test","parentWorkspace":"D:\/codes\/algorithm","name":"solution1.java","lastModified":1590199474787,"locationURI":"file:\/D:\/codes\/algorithm\/Programmers\/src\/test\/solution1.java"},{"path":"\/codeplus_algo_basic\/src\/data_structure1_practice","parentWorkspace":"D:\/codes\/algorithm","name":"Fe_stick.java","lastModified":1592806050868,"locationURI":"file:\/D:\/codes\/algorithm\/codeplus_algo_basic\/src\/data_structure1_practice\/Fe_stick.java"},{"path":"\/Baekjoon\/src\/bronze1","parentWorkspace":"D:\/codes\/algorithm","name":"palindrome.java","lastModified":1592673704600,"locationURI":"file:\/D:\/codes\/algorithm\/Baekjoon\/src\/bronze1\/palindrome.java"},{"path":"\/codeplus_algo_basic\/src\/data_structure_ref","parentWorkspace":"D:\/codes\/algorithm","name":"analysis_str.java","lastModified":1592895218903,"locationURI":"file:\/D:\/codes\/algorithm\/codeplus_algo_basic\/src\/data_structure_ref\/analysis_str.java"},{"path":"\/Algorithm_Study\/src\/graph_and_tree","parentWorkspace":"D:\/codes\/algorithm","name":"BuildingTreeFromTraversalResult.java","lastModified":1589970446140,"locationURI":"file:\/D:\/codes\/algorithm\/Algorithm_Study\/src\/graph_and_tree\/BuildingTreeFromTraversalResult.java"},{"path":"\/Baekjoon\/src\/bronze1","parentWorkspace":"D:\/codes\/algorithm","name":"hiddenNum.java","lastModified":1591839348034,"locationURI":"file:\/D:\/codes\/algorithm\/Baekjoon\/src\/bronze1\/hiddenNum.java"},{"path":"\/Algorithm_Study\/src\/graph_and_tree","parentWorkspace":"D:\/codes\/algorithm","name":"Graph_explaination.java","lastModified":1589210410741,"locationURI":"file:\/D:\/codes\/algorithm\/Algorithm_Study\/src\/graph_and_tree\/Graph_explaination.java"},{"path":"\/codeplus_algo_basic\/src\/data_structure_ref","parentWorkspace":"D:\/codes\/algorithm","name":"word_length.java","lastModified":1592895408068,"locationURI":"file:\/D:\/codes\/algorithm\/codeplus_algo_basic\/src\/data_structure_ref\/word_length.java"},{"path":"\/codeplus_algo_basic\/src\/data_structure1","parentWorkspace":"D:\/codes\/algorithm","name":"editor_stack.java","lastModified":1592754178162,"locationURI":"file:\/D:\/codes\/algorithm\/codeplus_algo_basic\/src\/data_structure1\/editor_stack.java"},{"path":"\/Algorithm_Study\/src\/graph_and_tree","parentWorkspace":"D:\/codes\/algorithm","name":"BinaryHeap.java","lastModified":1589198712655,"locationURI":"file:\/D:\/codes\/algorithm\/Algorithm_Study\/src\/graph_and_tree\/BinaryHeap.java"},{"path":"\/Programmers\/src\/test","parentWorkspace":"D:\/codes\/algorithm","name":"solution2.java","lastModified":1590200336288,"locationURI":"file:\/D:\/codes\/algorithm\/Programmers\/src\/test\/solution2.java"},{"path":"\/Algorithm_Study\/src\/data_structure","parentWorkspace":"D:\/codes\/algorithm","name":"binarySearch_ex1.java","lastModified":1592492029370,"locationURI":"file:\/D:\/codes\/algorithm\/Algorithm_Study\/src\/data_structure\/binarySearch_ex1.java"},{"path":"\/Algorithm_Study\/src\/data_structure","parentWorkspace":"D:\/codes\/algorithm","name":"bubbleSort.java","lastModified":1592553730451,"locationURI":"file:\/D:\/codes\/algorithm\/Algorithm_Study\/src\/data_structure\/bubbleSort.java"},{"path":"\/Baekjoon\/src\/bronze1","parentWorkspace":"D:\/codes\/algorithm","name":"pow.java","lastModified":1592675400394,"locationURI":"file:\/D:\/codes\/algorithm\/Baekjoon\/src\/bronze1\/pow.java"},{"path":"\/Baekjoon\/src\/bronze1","parentWorkspace":"D:\/codes\/algorithm","name":"nCr.java","lastModified":1591626373457,"locationURI":"file:\/D:\/codes\/algorithm\/Baekjoon\/src\/bronze1\/nCr.java"},{"path":"\/codeplus_algo_basic\/src\/data_structure1","parentWorkspace":"D:\/codes\/algorithm","name":"editor.java","lastModified":1592797314539,"locationURI":"file:\/D:\/codes\/algorithm\/codeplus_algo_basic\/src\/data_structure1\/editor.java"},{"path":"\/Algorithm_Study\/src\/graph_and_tree","parentWorkspace":"D:\/codes\/algorithm","name":"findPathBySumOfTree2.java","lastModified":1589970041509,"locationURI":"file:\/D:\/codes\/algorithm\/Algorithm_Study\/src\/graph_and_tree\/findPathBySumOfTree2.java"},{"path":"\/codeplus_algo_basic\/src\/data_structure1","parentWorkspace":"D:\/codes\/algorithm","name":"word_reverse.java","lastModified":1592738623428,"locationURI":"file:\/D:\/codes\/algorithm\/codeplus_algo_basic\/src\/data_structure1\/word_reverse.java"},{"path":"\/Baekjoon\/src\/bronze1","parentWorkspace":"D:\/codes\/algorithm","name":"PerfectSquare.java","lastModified":1591839348034,"locationURI":"file:\/D:\/codes\/algorithm\/Baekjoon\/src\/bronze1\/PerfectSquare.java"},{"path":"\/fast\/src\/basic_algo","parentWorkspace":"D:\/codes\/algorithm","name":"pro_2920.java","lastModified":1592648592306,"locationURI":"file:\/D:\/codes\/algorithm\/fast\/src\/basic_algo\/pro_2920.java"},{"path":"\/Baekjoon\/src\/baekjoon_fast","parentWorkspace":"D:\/codes\/algorithm","name":"printerQeue.java","lastModified":1592724184945,"locationURI":"file:\/D:\/codes\/algorithm\/Baekjoon\/src\/baekjoon_fast\/printerQeue.java"},{"path":"\/Algorithm_Study\/src\/graph_and_tree","parentWorkspace":"D:\/codes\/algorithm","name":"GraphSeach.java","lastModified":1589283969773,"locationURI":"file:\/D:\/codes\/algorithm\/Algorithm_Study\/src\/graph_and_tree\/GraphSeach.java"},{"path":"\/Algorithm_Study\/src\/data_structure","parentWorkspace":"D:\/codes\/algorithm","name":"IntStack.java","lastModified":1592020051137,"locationURI":"file:\/D:\/codes\/algorithm\/Algorithm_Study\/src\/data_structure\/IntStack.java"},{"path":"\/codeplus_algo_basic\/src\/data_structure1","parentWorkspace":"D:\/codes\/algorithm","name":"deque_test.java","lastModified":1592757432781,"locationURI":"file:\/D:\/codes\/algorithm\/codeplus_algo_basic\/src\/data_structure1\/deque_test.java"},{"path":"\/Algorithm_Study\/src\/graph_and_tree","parentWorkspace":"D:\/codes\/algorithm","name":"Graph_Road_twoNodes.java","lastModified":1589283983703,"locationURI":"file:\/D:\/codes\/algorithm\/Algorithm_Study\/src\/graph_and_tree\/Graph_Road_twoNodes.java"},{"path":"\/Algorithm_Study\/src\/data_structure","parentWorkspace":"D:\/codes\/algorithm","name":"selectionSort.java","lastModified":1592625481770,"locationURI":"file:\/D:\/codes\/algorithm\/Algorithm_Study\/src\/data_structure\/selectionSort.java"},{"path":"\/codeplus_algo_basic\/src\/data_structure1","parentWorkspace":"D:\/codes\/algorithm","name":"bracket.java","lastModified":1592747020759,"locationURI":"file:\/D:\/codes\/algorithm\/codeplus_algo_basic\/src\/data_structure1\/bracket.java"},{"path":"\/Algorithm_Study\/src\/graph_and_tree","parentWorkspace":"D:\/codes\/algorithm","name":"BinaryTree_Traversal.java","lastModified":1592016464206,"locationURI":"file:\/D:\/codes\/algorithm\/Algorithm_Study\/src\/graph_and_tree\/BinaryTree_Traversal.java"},{"path":"\/Algorithm_Study\/src\/graph_and_tree","parentWorkspace":"D:\/codes\/algorithm","name":"findPathBySumOfTree.java","lastModified":1589959751702,"locationURI":"file:\/D:\/codes\/algorithm\/Algorithm_Study\/src\/graph_and_tree\/findPathBySumOfTree.java"},{"path":"\/codeplus_algo_basic\/src\/data_structure_ref","parentWorkspace":"D:\/codes\/algorithm","name":"num_of_alphabet.java","lastModified":1592894344410,"locationURI":"file:\/D:\/codes\/algorithm\/codeplus_algo_basic\/src\/data_structure_ref\/num_of_alphabet.java"},{"path":"\/Algorithm_Study\/src\/graph_and_tree","parentWorkspace":"D:\/codes\/algorithm","name":"TriesTree.java","lastModified":1589267706606,"locationURI":"file:\/D:\/codes\/algorithm\/Algorithm_Study\/src\/graph_and_tree\/TriesTree.java"},{"path":"\/codeplus_algo_basic\/src\/data_structure_ref","parentWorkspace":"D:\/codes\/algorithm","name":"postOrder_stack.java","lastModified":1592894050376,"locationURI":"file:\/D:\/codes\/algorithm\/codeplus_algo_basic\/src\/data_structure_ref\/postOrder_stack.java"},{"path":"\/codeplus_algo_basic\/src\/data_structure_ref","parentWorkspace":"D:\/codes\/algorithm","name":"surffix_array.java","lastModified":1592904642434,"locationURI":"file:\/D:\/codes\/algorithm\/codeplus_algo_basic\/src\/data_structure_ref\/surffix_array.java"},{"path":"\/Algorithm_Study\/src\/graph_and_tree","parentWorkspace":"D:\/codes\/algorithm","name":"binaryTree_by_array.java","lastModified":1589285337360,"locationURI":"file:\/D:\/codes\/algorithm\/Algorithm_Study\/src\/graph_and_tree\/binaryTree_by_array.java"},{"path":"\/codeplus_algo_basic\/src\/data_structure1_practice","parentWorkspace":"D:\/codes\/algorithm","name":"NGF.java","lastModified":1592846986453,"locationURI":"file:\/D:\/codes\/algorithm\/codeplus_algo_basic\/src\/data_structure1_practice\/NGF.java"},{"path":"\/codeplus_algo_basic\/src\/data_structure1_practice","parentWorkspace":"D:\/codes\/algorithm","name":"NGE.java","lastModified":1592810464995,"locationURI":"file:\/D:\/codes\/algorithm\/codeplus_algo_basic\/src\/data_structure1_practice\/NGE.java"},{"path":"\/Baekjoon\/src\/bronze2","parentWorkspace":"D:\/codes\/algorithm","name":"palindrome.java","lastModified":1592033543224,"locationURI":"file:\/D:\/codes\/algorithm\/Baekjoon\/src\/bronze2\/palindrome.java"},{"path":"\/Baekjoon\/src\/bronze1","parentWorkspace":"D:\/codes\/algorithm","name":"vertical_read.java","lastModified":1591689654568,"locationURI":"file:\/D:\/codes\/algorithm\/Baekjoon\/src\/bronze1\/vertical_read.java"},{"path":"\/Algorithm_Study\/src\/graph_and_tree","parentWorkspace":"D:\/codes\/algorithm","name":"Stack.java","lastModified":1591874501442,"locationURI":"file:\/D:\/codes\/algorithm\/Algorithm_Study\/src\/graph_and_tree\/Stack.java"},{"path":"\/codeplus_algo_basic\/src\/data_structure1","parentWorkspace":"D:\/codes\/algorithm","name":"Josephus.java","lastModified":1592755991475,"locationURI":"file:\/D:\/codes\/algorithm\/codeplus_algo_basic\/src\/data_structure1\/Josephus.java"},{"path":"\/Algorithm_Study\/src\/graph_and_tree","parentWorkspace":"D:\/codes\/algorithm","name":"confirm_subtree.java","lastModified":1589904990034,"locationURI":"file:\/D:\/codes\/algorithm\/Algorithm_Study\/src\/graph_and_tree\/confirm_subtree.java"},{"path":"\/codeplus_algo_basic\/src","parentWorkspace":"D:\/codes\/algorithm","name":"Main.java","lastModified":1592842632331,"locationURI":"file:\/D:\/codes\/algorithm\/codeplus_algo_basic\/src\/Main.java"},{"path":"\/Baekjoon\/src\/bronze1","parentWorkspace":"D:\/codes\/algorithm","name":"print_original.java","lastModified":1591624042036,"locationURI":"file:\/D:\/codes\/algorithm\/Baekjoon\/src\/bronze1\/print_original.java"},{"path":"\/Baekjoon\/src\/bronze1","parentWorkspace":"D:\/codes\/algorithm","name":"word_study.java","lastModified":1591625834110,"locationURI":"file:\/D:\/codes\/algorithm\/Baekjoon\/src\/bronze1\/word_study.java"},{"path":"\/codeplus_algo_basic\/src\/data_structure_ref","parentWorkspace":"D:\/codes\/algorithm","name":"ROT13.java","lastModified":1592897186663,"locationURI":"file:\/D:\/codes\/algorithm\/codeplus_algo_basic\/src\/data_structure_ref\/ROT13.java"},{"path":"\/Algorithm_Study\/src\/graph_and_tree","parentWorkspace":"D:\/codes\/algorithm","name":"RandomNodeFromBST.java","lastModified":1589907047211,"locationURI":"file:\/D:\/codes\/algorithm\/Algorithm_Study\/src\/graph_and_tree\/RandomNodeFromBST.java"},{"path":"\/Algorithm_Study\/src\/graph_and_tree","parentWorkspace":"D:\/codes\/algorithm","name":"BinaryTree_to_LevelList.java","lastModified":1589294038408,"locationURI":"file:\/D:\/codes\/algorithm\/Algorithm_Study\/src\/graph_and_tree\/BinaryTree_to_LevelList.java"},{"path":"\/Programmers\/src\/Pro_Level1","parentWorkspace":"D:\/codes\/algorithm","name":"gcd_and_lcm.java","lastModified":1592030683513,"locationURI":"file:\/D:\/codes\/algorithm\/Programmers\/src\/Pro_Level1\/gcd_and_lcm.java"},{"path":"\/codeplus_algo_basic\/src\/data_structure1_practice","parentWorkspace":"D:\/codes\/algorithm","name":"word_reverse2.java","lastModified":1592802091118,"locationURI":"file:\/D:\/codes\/algorithm\/codeplus_algo_basic\/src\/data_structure1_practice\/word_reverse2.java"},{"path":"\/Baekjoon\/src\/bronze1","parentWorkspace":"D:\/codes\/algorithm","name":"year_2007.java","lastModified":1591839348034,"locationURI":"file:\/D:\/codes\/algorithm\/Baekjoon\/src\/bronze1\/year_2007.java"},{"path":"\/Algorithm_Study\/src\/data_structure","parentWorkspace":"D:\/codes\/algorithm","name":"binary_Search_ex05.java","lastModified":1592017881185,"locationURI":"file:\/D:\/codes\/algorithm\/Algorithm_Study\/src\/data_structure\/binary_Search_ex05.java"},{"path":"\/SWEA\/src\/intermediate","parentWorkspace":"D:\/codes\/algorithm","name":"Tree1_inOrder.java","lastModified":1589201238624,"locationURI":"file:\/D:\/codes\/algorithm\/SWEA\/src\/intermediate\/Tree1_inOrder.java"}]}